stups_ssh_tunnels-0.1.dist-info/DESCRIPTION.rst
stups_ssh_tunnels-0.1.dist-info/METADATA
stups_ssh_tunnels-0.1.dist-info/RECORD
stups_ssh_tunnels-0.1.dist-info/WHEEL
stups_ssh_tunnels-0.1.dist-info/entry_points.txt
stups_ssh_tunnels-0.1.dist-info/metadata.json
stups_ssh_tunnels-0.1.dist-info/top_level.txt
tunnels/__init__.py
tunnels/__main__.py
tunnels/cli.py
