Metadata-Version: 2.0
Name: stups-ssh-tunnels
Version: 0.1
Summary: Convenience tool to create SSH tunnels to cluster applications on AWS
Home-page: https://github.com/zalando-stups/ssh-tunnels
Author: Henning Jacobs
Author-email: henning.jacobs@zalando.de
License: Apache License 2.0
Keywords: tunnels aws stups
Platform: UNKNOWN
Requires-Dist: clickclick
